akmal/__init__.py
akmal/modul.py
akmal-0.2.dist-info/METADATA
akmal-0.2.dist-info/WHEEL
akmal-0.2.dist-info/top_level.txt
akmal-0.2.dist-info/RECORD
