Metadata-Version: 2.1
Name: akmal
Version: 0.2
Summary: orang tamvan
Author: akmal
Classifier: Programming Language :: Python :: 3
Classifier: License :: OSI Approved :: MIT License
Classifier: Operating System :: OS Independent
